django_user_verification-0.1.2.dist-info/DESCRIPTION.rst
django_user_verification-0.1.2.dist-info/METADATA
django_user_verification-0.1.2.dist-info/RECORD
django_user_verification-0.1.2.dist-info/WHEEL
django_user_verification-0.1.2.dist-info/metadata.json
django_user_verification-0.1.2.dist-info/top_level.txt
verification/__init__.py
verification/generators.py
verification/serializers.py
verification/services.py
verification/urls.py
verification/views.py
verification/__pycache__/__init__.cpython-35.pyc
verification/__pycache__/generators.cpython-35.pyc
verification/__pycache__/services.cpython-35.pyc
verification/__pycache__/urls.cpython-35.pyc
verification/__pycache__/views.cpython-35.pyc
verification/backends/__init__.py
verification/backends/base.py
verification/backends/email.py
verification/backends/twilio.py
verification/backends/__pycache__/__init__.cpython-35.pyc
verification/backends/__pycache__/base.cpython-35.pyc
verification/backends/__pycache__/email.cpython-35.pyc
verification/backends/__pycache__/twilio.cpython-35.pyc
verification/templates/verification/email.html
verification/templates/verification/email.txt
verification/templates/verification/redirector.html
