Metadata-Version: 2.0
Name: django-user-verification
Version: 0.1.2
Summary: Package to help out with verifying new users.
Home-page: https://github.com/Fueled/django-user-verification
Author: Shreyas & Paul
Author-email: backend@fueled.com
License: BSD
Keywords: django-user-verification
Platform: UNKNOWN
Classifier: Development Status :: 3 - Alpha
Classifier: Framework :: Django
Classifier: Framework :: Django :: 1.8
Classifier: Framework :: Django :: 1.9
Classifier: Intended Audience :: Developers
Classifier: License :: OSI Approved :: BSD License
Classifier: Natural Language :: English
Classifier: Programming Language :: Python :: 2
Classifier: Programming Language :: Python :: 2.7
Classifier: Programming Language :: Python :: 3
Classifier: Programming Language :: Python :: 3.3
Classifier: Programming Language :: Python :: 3.4
Classifier: Programming Language :: Python :: 3.5
Requires-Dist: djangorestframework (>=3.3.3)
Requires-Dist: twilio (>=5.4.0)
